Workbook

Sheet Segmentation Summary
B1: Median Total Investment (threshold) | C1: =MEDIAN('Client Features'!$M$2:$M$2001) -> 1220893.2
B2: Median Age (threshold) | C2: =MEDIAN('Client Features'!$D$2:$D$2001) -> 55
A4: Buyer Segmentation Summary
A5: Parcl Real Estate | Rule-based segmentation mirroring K-Means cluster logic (C1-C4 from PRD)
A7: Segment | B7: Clients | C7: Avg Investment | D7: Avg Satisfaction | E7: Avg Properties
A8: C1 - Global Investors | B8: =COUNTIF('Client Features'!$AH$2:$AH$2001,"C1 - Global Investors") -> 271 | C8: =IFERROR(AVERAGEIF('Client Features'!$AH$2:$AH$2001,"C1 - Global Investors",'Client Features'!$M$2:$M$2001),0) -> 1525767.3 | D8: =IFERROR(AVERAGEIF('Client Features'!$AH$2:$AH$2001,"C1 - Global Investors",'Client Features'!$I$2:$I$2001),0) -> 3.1254613 | E8: =IFERROR(AVERAGEIF('Client Features'!$AH$2:$AH$2001,"C1 - Global Investors",'Client Features'!$L$2:$L$2001),0) -> 4.0110701
A9: C2 - First-Time Buyers | B9: =COUNTIF('Client Features'!$AH$2:$AH$2001,"C2 - First-Time Buyers") -> 255 | C9: =IFERROR(AVERAGEIF('Client Features'!$AH$2:$AH$2001,"C2 - First-Time Buyers",'Client Features'!$M$2:$M$2001),0) -> 1135941.8 | D9: =IFERROR(AVERAGEIF('Client Features'!$AH$2:$AH$2001,"C2 - First-Time Buyers",'Client Features'!$I$2:$I$2001),0) -> 2.7803922 | E9: =IFERROR(AVERAGEIF('Client Features'!$AH$2:$AH$2001,"C2 - First-Time Buyers",'Client Features'!$L$2:$L$2001),0) -> 3.4901961
A10: C3 - Corporate Buyers | B10: =COUNTIF('Client Features'!$AH$2:$AH$2001,"C3 - Corporate Buyers") -> 103 | C10: =IFERROR(AVERAGEIF('Client Features'!$AH$2:$AH$2001,"C3 - Corporate Buyers",'Client Features'!$M$2:$M$2001),0) -> 1263753.5 | D10: =IFERROR(AVERAGEIF('Client Features'!$AH$2:$AH$2001,"C3 - Corporate Buyers",'Client Features'!$I$2:$I$2001),0) -> 3.0679612 | E10: =IFERROR(AVERAGEIF('Client Features'!$AH$2:$AH$2001,"C3 - Corporate Buyers",'Client Features'!$L$2:$L$2001),0) -> 3.6990291
A11: C4 - Luxury Investors | B11: =COUNTIF('Client Features'!$AH$2:$AH$2001,"C4 - Luxury Investors") -> 269 | C11: =IFERROR(AVERAGEIF('Client Features'!$AH$2:$AH$2001,"C4 - Luxury Investors",'Client Features'!$M$2:$M$2001),0) -> 1519650.8 | D11: =IFERROR(AVERAGEIF('Client Features'!$AH$2:$AH$2001,"C4 - Luxury Investors",'Client Features'!$I$2:$I$2001),0) -> 4.4944238 | E11: =IFERROR(AVERAGEIF('Client Features'!$AH$2:$AH$2001,"C4 - Luxury Investors",'Client Features'!$L$2:$L$2001),0) -> 4.0520446
A12: C5 - Other Individual Buyers | B12: =COUNTIF('Client Features'!$AH$2:$AH$2001,"C5 - Other Individual Buyers") -> 1102 | C12: =IFERROR(AVERAGEIF('Client Features'!$AH$2:$AH$2001,"C5 - Other Individual Buyers",'Client Features'!$M$2:$M$2001),0) -> 1160299.6 | D12: =IFERROR(AVERAGEIF('Client Features'!$AH$2:$AH$2001,"C5 - Other Individual Buyers",'Client Features'!$I$2:$I$2001),0) -> 2.7014519 | E12: =IFERROR(AVERAGEIF('Client Features'!$AH$2:$AH$2001,"C5 - Other Individual Buyers",'Client Features'!$L$2:$L$2001),0) -> 3.5
A36: Segment Definitions (as classified by the formulas)
A37: C1 - Global Investors | B37: Acquisition purpose = Investment, and total investment above the median — high-value investment-driven buyers.
A38: C2 - First-Time Buyers | B38: Below-median age and used loan financing — younger buyers who are financing their purchase.
A39: C3 - Corporate Buyers | B39: Client type = Company — institutional buyers purchasing on behalf of an organization.
A40: C4 - Luxury Investors | B40: Satisfaction score 4-5 and total investment above the median — highly satisfied, high-value buyers.
A41: C5 - Other Individual Buyers | B41: Individual buyers who don't meet the above criteria — typically standard home buyers.

Sheet EDA Dashboard
A1: Buyer Segmentation — Exploratory Data Analysis
A2: Parcl Real Estate | 2,000 clients, all data cleaned & joined via SQL
A4: FILTERS
A5: Country | B5: All | D5: =IF(B5="All","*",B5) -> *
A6: Client Type | B6: All | D6: =IF(B6="All","*",B6) -> *
A7: Acquisition Purpose | B7: All | D7: =IF(B7="All","*",B7) -> *
A9: KEY METRICS
A10: Clients Matching Filters | B10: =COUNTIFS('Client Features'!$F$2:$F$2001,$D$5,'Client Features'!$B$2:$B$2001,$D$6,'Client Features'!$H$2:$H$2001,$D$7) -> 2000
A11: Avg. Total Investment | B11: =AVERAGEIFS('Client Features'!$M$2:$M$2001,'Client Features'!$F$2:$F$2001,$D$5,'Client Features'!$B$2:$B$2001,$D$6,'Client Features'!$H$2:$H$2001,$D$7) -> 1260375.5
A12: Avg. Satisfaction Score | B12: =AVERAGEIFS('Client Features'!$I$2:$I$2001,'Client Features'!$F$2:$F$2001,$D$5,'Client Features'!$B$2:$B$2001,$D$6,'Client Features'!$H$2:$H$2001,$D$7) -> 3.029
A13: Avg. Properties Purchased | B13: =AVERAGEIFS('Client Features'!$L$2:$L$2001,'Client Features'!$F$2:$F$2001,$D$5,'Client Features'!$B$2:$B$2001,$D$6,'Client Features'!$H$2:$H$2001,$D$7) -> 3.6525
A14: % Using Loan Financing | B14: =AVERAGEIFS('Client Features'!$J$2:$J$2001,'Client Features'!$F$2:$F$2001,$D$5,'Client Features'!$B$2:$B$2001,$D$6,'Client Features'!$H$2:$H$2001,$D$7) -> 0.368
A16: Country | B16: Clients | C16: Avg Investment | E16: Client Type | F16: Clients | G16: Avg Investment
A17: USA | B17: =COUNTIFS('Client Features'!$F$2:$F$2001,"USA",'Client Features'!$B$2:$B$2001,$D$6,'Client Features'!$H$2:$H$2001,$D$7) -> 1538 | C17: =IFERROR(AVERAGEIFS('Client Features'!$M$2:$M$2001,'Client Features'!$F$2:$F$2001,"USA",'Client Features'!$B$2:$B$2001,$D$6,'Client Features'!$H$2:$H$2001,$D$7),0) -> 1269852 | E17: Individual | F17: =COUNTIFS('Client Features'!$B$2:$B$2001,"Individual",'Client Features'!$F$2:$F$2001,$D$5,'Client Features'!$H$2:$H$2001,$D$7) -> 1897 | G17: =IFERROR(AVERAGEIFS('Client Features'!$M$2:$M$2001,'Client Features'!$B$2:$B$2001,"Individual",'Client Features'!$F$2:$F$2001,$D$5,'Client Features'!$H$2:$H$2001,$D$7),0) -> 1260192.1
A18: UK | B18: =COUNTIFS('Client Features'!$F$2:$F$2001,"UK",'Client Features'!$B$2:$B$2001,$D$6,'Client Features'!$H$2:$H$2001,$D$7) -> 95 | C18: =IFERROR(AVERAGEIFS('Client Features'!$M$2:$M$2001,'Client Features'!$F$2:$F$2001,"UK",'Client Features'!$B$2:$B$2001,$D$6,'Client Features'!$H$2:$H$2001,$D$7),0) -> 1284490.3 | E18: Company | F18: =COUNTIFS('Client Features'!$B$2:$B$2001,"Company",'Client Features'!$F$2:$F$2001,$D$5,'Client Features'!$H$2:$H$2001,$D$7) -> 103 | G18: =IFERROR(AVERAGEIFS('Client Features'!$M$2:$M$2001,'Client Features'!$B$2:$B$2001,"Company",'Client Features'!$F$2:$F$2001,$D$5,'Client Features'!$H$2:$H$2001,$D$7),0) -> 1263753.5
A19: Canada | B19: =COUNTIFS('Client Features'!$F$2:$F$2001,"Canada",'Client Features'!$B$2:$B$2001,$D$6,'Client Features'!$H$2:$H$2001,$D$7) -> 85 | C19: =IFERROR(AVERAGEIFS('Client Features'!$M$2:$M$2001,'Client Features'!$F$2:$F$2001,"Canada",'Client Features'!$B$2:$B$2001,$D$6,'Client Features'!$H$2:$H$2001,$D$7),0) -> 1207422.9
A20: Germany | B20: =COUNTIFS('Client Features'!$F$2:$F$2001,"Germany",'Client Features'!$B$2:$B$2001,$D$6,'Client Features'!$H$2:$H$2001,$D$7) -> 56 | C20: =IFERROR(AVERAGEIFS('Client Features'!$M$2:$M$2001,'Client Features'!$F$2:$F$2001,"Germany",'Client Features'!$B$2:$B$2001,$D$6,'Client Features'!$H$2:$H$2001,$D$7),0) -> 1194135.2 | E20: Purpose | F20: Clients | G20: Avg Investment
A21: France | B21: =COUNTIFS('Client Features'!$F$2:$F$2001,"France",'Client Features'!$B$2:$B$2001,$D$6,'Client Features'!$H$2:$H$2001,$D$7) -> 53 | C21: =IFERROR(AVERAGEIFS('Client Features'!$M$2:$M$2001,'Client Features'!$F$2:$F$2001,"France",'Client Features'!$B$2:$B$2001,$D$6,'Client Features'!$H$2:$H$2001,$D$7),0) -> 1224509.5 | E21: Home | F21: =COUNTIFS('Client Features'!$H$2:$H$2001,"Home",'Client Features'!$F$2:$F$2001,$D$5,'Client Features'!$B$2:$B$2001,$D$6) -> 1385 | G21: =IFERROR(AVERAGEIFS('Client Features'!$M$2:$M$2001,'Client Features'!$H$2:$H$2001,"Home",'Client Features'!$F$2:$F$2001,$D$5,'Client Features'!$B$2:$B$2001,$D$6),0) -> 1263587.6
A22: Belgium | B22: =COUNTIFS('Client Features'!$F$2:$F$2001,"Belgium",'Client Features'!$B$2:$B$2001,$D$6,'Client Features'!$H$2:$H$2001,$D$7) -> 43 | C22: =IFERROR(AVERAGEIFS('Client Features'!$M$2:$M$2001,'Client Features'!$F$2:$F$2001,"Belgium",'Client Features'!$B$2:$B$2001,$D$6,'Client Features'!$H$2:$H$2001,$D$7),0) -> 1261068.2 | E22: Investment | F22: =COUNTIFS('Client Features'!$H$2:$H$2001,"Investment",'Client Features'!$F$2:$F$2001,$D$5,'Client Features'!$B$2:$B$2001,$D$6) -> 615 | G22: =IFERROR(AVERAGEIFS('Client Features'!$M$2:$M$2001,'Client Features'!$H$2:$H$2001,"Investment",'Client Features'!$F$2:$F$2001,$D$5,'Client Features'!$B$2:$B$2001,$D$6),0) -> 1253141.8
A23: Mexico | B23: =COUNTIFS('Client Features'!$F$2:$F$2001,"Mexico",'Client Features'!$B$2:$B$2001,$D$6,'Client Features'!$H$2:$H$2001,$D$7) -> 40 | C23: =IFERROR(AVERAGEIFS('Client Features'!$M$2:$M$2001,'Client Features'!$F$2:$F$2001,"Mexico",'Client Features'!$B$2:$B$2001,$D$6,'Client Features'!$H$2:$H$2001,$D$7),0) -> 1210743.7
A24: Australia | B24: =COUNTIFS('Client Features'!$F$2:$F$2001,"Australia",'Client Features'!$B$2:$B$2001,$D$6,'Client Features'!$H$2:$H$2001,$D$7) -> 39 | C24: =IFERROR(AVERAGEIFS('Client Features'!$M$2:$M$2001,'Client Features'!$F$2:$F$2001,"Australia",'Client Features'!$B$2:$B$2001,$D$6,'Client Features'!$H$2:$H$2001,$D$7),0) -> 1124868.1
A25: Russia | B25: =COUNTIFS('Client Features'!$F$2:$F$2001,"Russia",'Client Features'!$B$2:$B$2001,$D$6,'Client Features'!$H$2:$H$2001,$D$7) -> 36 | C25: =IFERROR(AVERAGEIFS('Client Features'!$M$2:$M$2001,'Client Features'!$F$2:$F$2001,"Russia",'Client Features'!$B$2:$B$2001,$D$6,'Client Features'!$H$2:$H$2001,$D$7),0) -> 1240606.3
A26: Denmark | B26: =COUNTIFS('Client Features'!$F$2:$F$2001,"Denmark",'Client Features'!$B$2:$B$2001,$D$6,'Client Features'!$H$2:$H$2001,$D$7) -> 15 | C26: =IFERROR(AVERAGEIFS('Client Features'!$M$2:$M$2001,'Client Features'!$F$2:$F$2001,"Denmark",'Client Features'!$B$2:$B$2001,$D$6,'Client Features'!$H$2:$H$2001,$D$7),0) -> 1340203.6

Sheet Client Features
A1: client_id | B1: client_type | C1: full_name | D1: age | E1: gender | F1: country | G1: region | H1: acquisition_purpose | I1: satisfaction_score | J1: loan_applied_flag | K1: referral_channel | L1: num_properties_purchased | M1: total_investment_value | N1: avg_purchase_price | O1: avg_floor_area_sqft | P1: num_office_units | Q1: num_apartment_units | R1: first_purchase_date | S1: last_purchase_date | T1: is_repeat_buyer | U1: type_Individual | V1: type_Company | W1: purpose_Home | X1: purpose_Investment | Y1: referral_Website | Z1: referral_Agency | AA1: referral_Client | AB1: age_z | AC1: satisfaction_z | AD1: num_purchased_z | AE1: total_investment_z | AF1: avg_price_z | AG1: avg_area_z | AH1: Segment
A2: C0128 | B2: Company | C2: Abdiel Co | D2: 61 | E2: M | F2: USA | G2: Nevada | H2: Investment | I2: 5 | J2: 1 | K2: Website | L2: 5 | M2: 1639392.9 | N2: 327878.59 | O2: 1054.034 | P2: 1 | Q2: 4 | R2: 2024-01-05 | S2: 2025-01-12 | T2: 1 | U2: =IF(B2="Individual",1,0) -> 0 | V2: =IF(B2="Company",1,0) -> 1 | W2: =IF(H2="Home",1,0) -> 0 | X2: =IF(H2="Investment",1,0) -> 1 | Y2: =IF(K2="Website",1,0) -> 1 | Z2: =IF(K2="Agency",1,0) -> 0 | AA2: =IF(K2="Client",1,0) -> 0 | AB2: =(D2-AVERAGE(D$2:D$2001))/STDEV(D$2:D$2001) -> 0.39573743 | AC2: =(I2-AVERAGE(I$2:I$2001))/STDEV(I$2:I$2001) -> 1.3943497 | AD2: =(L2-AVERAGE(L$2:L$2001))/STDEV(L$2:L$2001) -> 1.6047396 | AE2: =(M2-AVERAGE(M$2:M$2001))/STDEV(M$2:M$2001) -> 1.0896609 | AF2: =(N2-AVERAGE(N$2:N$2001))/STDEV(N$2:N$2001) -> -0.27554308 | AG2: =(O2-AVERAGE(O$2:O$2001))/STDEV(O$2:O$2001) -> -0.42490255 | AH2: =IF(B2="Company","C3 - Corporate Buyers",IF(AND(H2="Investment",M2>'Segmentation Summary'!$C$1),"C1 - Global Investors",IF(AND(I2>=4,M2>'Segmentation Summary'!$C$1),"C4 - Luxury Investors",IF(AND(D2<'Segmentation Summary'!$C$2,J2=1),"C2 - First-Time Buyers","C5 - Other Individual Buyers")))) -> C3 - Corporate Buyers
A3: C0454 | B3: Company | C3: Altira Co | D3: 64 | E3: F | F3: USA | G3: Nevada | H3: Investment | I3: 4 | J3: 0 | K3: Agency | L3: 3 | M3: 980683.73 | N3: 326894.58 | O3: 1072.4833 | P3: 0 | Q3: 3 | R3: 2024-01-01 | S3: 2024-01-11 | T3: 1 | U3: =IF(B3="Individual",1,0) -> 0 | V3: =IF(B3="Company",1,0) -> 1 | W3: =IF(H3="Home",1,0) -> 0 | X3: =IF(H3="Investment",1,0) -> 1 | Y3: =IF(K3="Website",1,0) -> 0 | Z3: =IF(K3="Agency",1,0) -> 1 | AA3: =IF(K3="Client",1,0) -> 0 | AB3: =(D3-AVERAGE(D$2:D$2001))/STDEV(D$2:D$2001) -> 0.5687248 | AC3: =(I3-AVERAGE(I$2:I$2001))/STDEV(I$2:I$2001) -> 0.68691707 | AD3: =(L3-AVERAGE(L$2:L$2001))/STDEV(L$2:L$2001) -> -0.77706312 | AE3: =(M3-AVERAGE(M$2:M$2001))/STDEV(M$2:M$2001) -> -0.8041032 | AF3: =(N3-AVERAGE(N$2:N$2001))/STDEV(N$2:N$2001) -> -0.2896565 | AG3: =(O3-AVERAGE(O$2:O$2001))/STDEV(O$2:O$2001) -> -0.34101242 | AH3: =IF(B3="Company","C3 - Corporate Buyers",IF(AND(H3="Investment",M3>'Segmentation Summary'!$C$1),"C1 - Global Investors",IF(AND(I3>=4,M3>'Segmentation Summary'!$C$1),"C4 - Luxury Investors",IF(AND(D3<'Segmentation Summary'!$C$2,J3=1),"C2 - First-Time Buyers","C5 - Other Individual Buyers")))) -> C3 - Corporate Buyers
A4: C1510 | B4: Company | C4: Altira Co | D4: 63 | E4: M | F4: USA | G4: California | H4: Home | I4: 5 | J4: 0 | K4: Agency | L4: 3 | M4: 804243.22 | N4: 268081.07 | O4: 842.68 | P4: 0 | Q4: 3 | R4: 2024-01-05 | S4: 2025-01-12 | T4: 1 | U4: =IF(B4="Individual",1,0) -> 0 | V4: =IF(B4="Company",1,0) -> 1 | W4: =IF(H4="Home",1,0) -> 1 | X4: =IF(H4="Investment",1,0) -> 0 | Y4: =IF(K4="Website",1,0) -> 0 | Z4: =IF(K4="Agency",1,0) -> 1 | AA4: =IF(K4="Client",1,0) -> 0 | AB4: =(D4-AVERAGE(D$2:D$2001))/STDEV(D$2:D$2001) -> 0.51106234 | AC4: =(I4-AVERAGE(I$2:I$2001))/STDEV(I$2:I$2001) -> 1.3943497 | AD4: =(L4-AVERAGE(L$2:L$2001))/STDEV(L$2:L$2001) -> -0.77706312 | AE4: =(M4-AVERAGE(M$2:M$2001))/STDEV(M$2:M$2001) -> -1.311363 | AF4: =(N4-AVERAGE(N$2:N$2001))/STDEV(N$2:N$2001) -> -1.1332016 | AG4: =(O4-AVERAGE(O$2:O$2001))/STDEV(O$2:O$2001) -> -1.3859407 | AH4: =IF(B4="Company","C3 - Corporate Buyers",IF(AND(H4="Investment",M4>'Segmentation Summary'!$C$1),"C1 - Global Investors",IF(AND(I4>=4,M4>'Segmentation Summary'!$C$1),"C4 - Luxury Investors",IF(AND(D4<'Segmentation Summary'!$C$2,J4=1),"C2 - First-Time Buyers","C5 - Other Individual Buyers")))) -> C3 - Corporate Buyers
A5: C0573 | B5: Company | C5: Altira Co | D5: 47 | E5: M | F5: USA | G5: Georgia | H5: Home | I5: 4 | J5: 1 | K5: Agency | L5: 3 | M5: 785842.76 | N5: 261947.59 | O5: 849.74667 | P5: 0 | Q5: 3 | R5: 2024-01-03 | S5: 2024-01-11 | T5: 1 | U5: =IF(B5="Individual",1,0) -> 0 | V5: =IF(B5="Company",1,0) -> 1 | W5: =IF(H5="Home",1,0) -> 1 | X5: =IF(H5="Investment",1,0) -> 0 | Y5: =IF(K5="Website",1,0) -> 0 | Z5: =IF(K5="Agency",1,0) -> 1 | AA5: =IF(K5="Client",1,0) -> 0 | AB5: =(D5-AVERAGE(D$2:D$2001))/STDEV(D$2:D$2001) -> -0.41153694 | AC5: =(I5-AVERAGE(I$2:I$2001))/STDEV(I$2:I$2001) -> 0.68691707 | AD5: =(L5-AVERAGE(L$2:L$2001))/STDEV(L$2:L$2001) -> -0.77706312 | AE5: =(M5-AVERAGE(M$2:M$2001))/STDEV(M$2:M$2001) -> -1.3642636 | AF5: =(N5-AVERAGE(N$2:N$2001))/STDEV(N$2:N$2001) -> -1.2211725 | AG5: =(O5-AVERAGE(O$2:O$2001))/STDEV(O$2:O$2001) -> -1.3538082 | AH5: =IF(B5="Company","C3 - Corporate Buyers",IF(AND(H5="Investment",M5>'Segmentation Summary'!$C$1),"C1 - Global Investors",IF(AND(I5>=4,M5>'Segmentation Summary'!$C$1),"C4 - Luxury Investors",IF(AND(D5<'Segmentation Summary'!$C$2,J5=1),"C2 - First-Time Buyers","C5 - Other Individual Buyers")))) -> C3 - Corporate Buyers
A6: C1856 | B6: Company | C6: Altira Co | D6: 30 | E6: M | F6: USA | G6: Virginia | H6: Home | I6: 2 | J6: 0 | K6: Website | L6: 3 | M6: 1216231.4 | N6: 405410.48 | O6: 1334.1 | P6: 0 | Q6: 3 | R6: 2024-01-02 | S6: 2024-01-11 | T6: 1 | U6: =IF(B6="Individual",1,0) -> 0 | V6: =IF(B6="Company",1,0) -> 1 | W6: =IF(H6="Home",1,0) -> 1 | X6: =IF(H6="Investment",1,0) -> 0 | Y6: =IF(K6="Website",1,0) -> 1 | Z6: =IF(K6="Agency",1,0) -> 0 | AA6: =IF(K6="Client",1,0) -> 0 | AB6: =(D6-AVERAGE(D$2:D$2001))/STDEV(D$2:D$2001) -> -1.3917987 | AC6: =(I6-AVERAGE(I$2:I$2001))/STDEV(I$2:I$2001) -> -0.72794816 | AD6: =(L6-AVERAGE(L$2:L$2001))/STDEV(L$2:L$2001) -> -0.77706312 | AE6: =(M6-AVERAGE(M$2:M$2001))/STDEV(M$2:M$2001) -> -0.12691247 | AF6: =(N6-AVERAGE(N$2:N$2001))/STDEV(N$2:N$2001) -> 0.83647442 | AG6: =(O6-AVERAGE(O$2:O$2001))/STDEV(O$2:O$2001) -> 0.84857283 | AH6: =IF(B6="Company","C3 - Corporate Buyers",IF(AND(H6="Investment",M6>'Segmentation Summary'!$C$1),"C1 - Global Investors",IF(AND(I6>=4,M6>'Segmentation Summary'!$C$1),"C4 - Luxury Investors",IF(AND(D6<'Segmentation Summary'!$C$2,J6=1),"C2 - First-Time Buyers","C5 - Other Individual Buyers")))) -> C3 - Corporate Buyers
A7: C0670 | B7: Company | C7: Altira Co | D7: 48 | E7: M | F7: USA | G7: Nevada | H7: Investment | I7: 4 | J7: 0 | K7: Website | L7: 3 | M7: 1631973.6 | N7: 543991.18 | O7: 1800.45 | P7: 0 | Q7: 3 | R7: 2024-01-02 | S7: 2025-01-01 | T7: 1 | U7: =IF(B7="Individual",1,0) -> 0 | V7: =IF(B7="Company",1,0) -> 1 | W7: =IF(H7="Home",1,0) -> 0 | X7: =IF(H7="Investment",1,0) -> 1 | Y7: =IF(K7="Website",1,0) -> 1 | Z7: =IF(K7="Agency",1,0) -> 0 | AA7: =IF(K7="Client",1,0) -> 0 | AB7: =(D7-AVERAGE(D$2:D$2001))/STDEV(D$2:D$2001) -> -0.35387449 | AC7: =(I7-AVERAGE(I$2:I$2001))/STDEV(I$2:I$2001) -> 0.68691707 | AD7: =(L7-AVERAGE(L$2:L$2001))/STDEV(L$2:L$2001) -> -0.77706312 | AE7: =(M7-AVERAGE(M$2:M$2001))/STDEV(M$2:M$2001) -> 1.0683304 | AF7: =(N7-AVERAGE(N$2:N$2001))/STDEV(N$2:N$2001) -> 2.8240976 | AG7: =(O7-AVERAGE(O$2:O$2001))/STDEV(O$2:O$2001) -> 2.9690917 | AH7: =IF(B7="Company","C3 - Corporate Buyers",IF(AND(H7="Investment",M7>'Segmentation Summary'!$C$1),"C1 - Global Investors",IF(AND(I7>=4,M7>'Segmentation Summary'!$C$1),"C4 - Luxury Investors",IF(AND(D7<'Segmentation Summary'!$C$2,J7=1),"C2 - First-Time Buyers","C5 - Other Individual Buyers")))) -> C3 - Corporate Buyers
A8: C0899 | B8: Company | C8: Apex Co | D8: 36 | E8: F | F8: USA | G8: Washington | H8: Investment | I8: 2 | J8: 0 | K8: Website | L8: 3 | M8: 1050407.6 | N8: 350135.88 | O8: 1076.69 | P8: 0 | Q8: 3 | R8: 2024-01-11 | S8: 2025-01-02 | T8: 1 | U8: =IF(B8="Individual",1,0) -> 0 | V8: =IF(B8="Company",1,0) -> 1 | W8: =IF(H8="Home",1,0) -> 0 | X8: =IF(H8="Investment",1,0) -> 1 | Y8: =IF(K8="Website",1,0) -> 1 | Z8: =IF(K8="Agency",1,0) -> 0 | AA8: =IF(K8="Client",1,0) -> 0 | AB8: =(D8-AVERAGE(D$2:D$2001))/STDEV(D$2:D$2001) -> -1.045824 | AC8: =(I8-AVERAGE(I$2:I$2001))/STDEV(I$2:I$2001) -> -0.72794816 | AD8: =(L8-AVERAGE(L$2:L$2001))/STDEV(L$2:L$2001) -> -0.77706312 | AE8: =(M8-AVERAGE(M$2:M$2001))/STDEV(M$2:M$2001) -> -0.60364963 | AF8: =(N8-AVERAGE(N$2:N$2001))/STDEV(N$2:N$2001) -> 0.043686764 | AG8: =(O8-AVERAGE(O$2:O$2001))/STDEV(O$2:O$2001) -> -0.32188448 | AH8: =IF(B8="Company","C3 - Corporate Buyers",IF(AND(H8="Investment",M8>'Segmentation Summary'!$C$1),"C1 - Global Investors",IF(AND(I8>=4,M8>'Segmentation Summary'!$C$1),"C4 - Luxury Investors",IF(AND(D8<'Segmentation Summary'!$C$2,J8=1),"C2 - First-Time Buyers","C5 - Other Individual Buyers")))) -> C3 - Corporate Buyers
A9: C1317 | B9: Company | C9: Atlas Co | D9: 51 | E9: M | F9: USA | G9: Utah | H9: Home | I9: 2 | J9: 1 | K9: Website | L9: 3 | M9: 1315200.1 | N9: 438400.04 | O9: 1460.4933 | P9: 0 | Q9: 3 | R9: 2024-01-08 | S9: 2025-01-03 | T9: 1 | U9: =IF(B9="Individual",1,0) -> 0 | V9: =IF(B9="Company",1,0) -> 1 | W9: =IF(H9="Home",1,0) -> 1 | X9: =IF(H9="Investment",1,0) -> 0 | Y9: =IF(K9="Website",1,0) -> 1 | Z9: =IF(K9="Agency",1,0) -> 0 | AA9: =IF(K9="Client",1,0) -> 0 | AB9: =(D9-AVERAGE(D$2:D$2001))/STDEV(D$2:D$2001) -> -0.18088712 | AC9: =(I9-AVERAGE(I$2:I$2001))/STDEV(I$2:I$2001) -> -0.72794816 | AD9: =(L9-AVERAGE(L$2:L$2001))/STDEV(L$2:L$2001) -> -0.77706312 | AE9: =(M9-AVERAGE(M$2:M$2001))/STDEV(M$2:M$2001) -> 0.15761876 | AF9: =(N9-AVERAGE(N$2:N$2001))/STDEV(N$2:N$2001) -> 1.3096342 | AG9: =(O9-AVERAGE(O$2:O$2001))/STDEV(O$2:O$2001) -> 1.4232902 | AH9: =IF(B9="Company","C3 - Corporate Buyers",IF(AND(H9="Investment",M9>'Segmentation Summary'!$C$1),"C1 - Global Investors",IF(AND(I9>=4,M9>'Segmentation Summary'!$C$1),"C4 - Luxury Investors",IF(AND(D9<'Segmentation Summary'!$C$2,J9=1),"C2 - First-Time Buyers","C5 - Other Individual Buyers")))) -> C3 - Corporate Buyers
A10: C0221 | B10: Company | C10: Atlas Co | D10: 37 | E10: F | F10: USA | G10: California | H10: Home | I10: 5 | J10: 0 | K10: Website | L10: 4 | M10: 1377133.6 | N10: 344283.4 | O10: 1186.5225 | P10: 0 | Q10: 4 | R10: 2024-01-11 | S10: 2025-01-10 | T10: 1 | U10: =IF(B10="Individual",1,0) -> 0 | V10: =IF(B10="Company",1,0) -> 1 | W10: =IF(H10="Home",1,0) -> 1 | X10: =IF(H10="Investment",1,0) -> 0 | Y10: =IF(K10="Website",1,0) -> 1 | Z10: =IF(K10="Agency",1,0) -> 0 | AA10: =IF(K10="Client",1,0) -> 0 | AB10: =(D10-AVERAGE(D$2:D$2001))/STDEV(D$2:D$2001) -> -0.9881615 | AC10: =(I10-AVERAGE(I$2:I$2001))/STDEV(I$2:I$2001) -> 1.3943497 | AD10: =(L10-AVERAGE(L$2:L$2001))/STDEV(L$2:L$2001) -> 0.41383821 | AE10: =(M10-AVERAGE(M$2:M$2001))/STDEV(M$2:M$2001) -> 0.33567518 | AF10: =(N10-AVERAGE(N$2:N$2001))/STDEV(N$2:N$2001) -> -0.040253622 | AG10: =(O10-AVERAGE(O$2:O$2001))/STDEV(O$2:O$2001) -> 0.17752989 | AH10: =IF(B10="Company","C3 - Corporate Buyers",IF(AND(H10="Investment",M10>'Segmentation Summary'!$C$1),"C1 - Global Investors",IF(AND(I10>=4,M10>'Segmentation Summary'!$C$1),"C4 - Luxury Investors",IF(AND(D10<'Segmentation Summary'!$C$2,J10=1),"C2 - First-Time Buyers","C5 - Other Individual Buyers")))) -> C3 - Corporate Buyers
A11: C1771 | B11: Company | C11: Atlas Co | D11: 49 | E11: M | F11: USA | G11: Georgia | H11: Home | I11: 3 | J11: 1 | K11: Client | L11: 3 | M11: 1280896 | N11: 426965.32 | O11: 1435.6633 | P11: 0 | Q11: 3 | R11: 2024-01-04 | S11: 2024-01-11 | T11: 1 | U11: =IF(B11="Individual",1,0) -> 0 | V11: =IF(B11="Company",1,0) -> 1 | W11: =IF(H11="Home",1,0) -> 1 | X11: =IF(H11="Investment",1,0) -> 0 | Y11: =IF(K11="Website",1,0) -> 0 | Z11: =IF(K11="Agency",1,0) -> 0 | AA11: =IF(K11="Client",1,0) -> 1 | AB11: =(D11-AVERAGE(D$2:D$2001))/STDEV(D$2:D$2001) -> -0.29621203 | AC11: =(I11-AVERAGE(I$2:I$2001))/STDEV(I$2:I$2001) -> -0.020515546 | AD11: =(L11-AVERAGE(L$2:L$2001))/STDEV(L$2:L$2001) -> -0.77706312 | AE11: =(M11-AVERAGE(M$2:M$2001))/STDEV(M$2:M$2001) -> 0.058995631 | AF11: =(N11-AVERAGE(N$2:N$2001))/STDEV(N$2:N$2001) -> 1.1456294 | AG11: =(O11-AVERAGE(O$2:O$2001))/STDEV(O$2:O$2001) -> 1.3103868 | AH11: =IF(B11="Company","C3 - Corporate Buyers",IF(AND(H11="Investment",M11>'Segmentation Summary'!$C$1),"C1 - Global Investors",IF(AND(I11>=4,M11>'Segmentation Summary'!$C$1),"C4 - Luxury Investors",IF(AND(D11<'Segmentation Summary'!$C$2,J11=1),"C2 - First-Time Buyers","C5 - Other Individual Buyers")))) -> C3 - Corporate Buyers
A12: C0561 | B12: Company | C12: Bravada Co | D12: 62 | E12: F | F12: USA | G12: Arizona | H12: Investment | I12: 3 | J12: 0 | K12: Website | L12: 4 | M12: 1589252.4 | N12: 397313.11 | O12: 1298.145 | P12: 0 | Q12: 4 | R12: 2024-01-06 | S12: 2025-01-01 | T12: 1 | U12: =IF(B12="Individual",1,0) -> 0 | V12: =IF(B12="Company",1,0) -> 1 | W12: =IF(H12="Home",1,0) -> 0 | X12: =IF(H12="Investment",1,0) -> 1 | Y12: =IF(K12="Website",1,0) -> 1 | Z12: =IF(K12="Agency",1,0) -> 0 | AA12: =IF(K12="Client",1,0) -> 0 | AB12: =(D12-AVERAGE(D$2:D$2001))/STDEV(D$2:D$2001) -> 0.45339989 | AC12: =(I12-AVERAGE(I$2:I$2001))/STDEV(I$2:I$2001) -> -0.020515546 | AD12: =(L12-AVERAGE(L$2:L$2001))/STDEV(L$2:L$2001) -> 0.41383821 | AE12: =(M12-AVERAGE(M$2:M$2001))/STDEV(M$2:M$2001) -> 0.94550879 | AF12: =(N12-AVERAGE(N$2:N$2001))/STDEV(N$2:N$2001) -> 0.72033619 | AG12: =(O12-AVERAGE(O$2:O$2001))/STDEV(O$2:O$2001) -> 0.68508348 | AH12: =IF(B12="Company","C3 - Corporate Buyers",IF(AND(H12="Investment",M12>'Segmentation Summary'!$C$1),"C1 - Global Investors",IF(AND(I12>=4,M12>'Segmentation Summary'!$C$1),"C4 - Luxury Investors",IF(AND(D12<'Segmentation Summary'!$C$2,J12=1),"C2 - First-Time Buyers","C5 - Other Individual Buyers")))) -> C3 - Corporate Buyers
A13: C1876 | B13: Company | C13: Bravada Co | D13: 43 | E13: M | F13: USA | G13: Ohio | H13: Investment | I13: 4 | J13: 1 | K13: Website | L13: 3 | M13: 1543986.3 | N13: 514662.11 | O13: 1523.6933 | P13: 0 | Q13: 3 | R13: 2024-01-07 | S13: 2025-01-11 | T13: 1 | U13: =IF(B13="Individual",1,0) -> 0 | V13: =IF(B13="Company",1,0) -> 1 | W13: =IF(H13="Home",1,0) -> 0 | X13: =IF(H13="Investment",1,0) -> 1 | Y13: =IF(K13="Website",1,0) -> 1 | Z13: =IF(K13="Agency",1,0) -> 0 | AA13: =IF(K13="Client",1,0) -> 0 | AB13: =(D13-AVERAGE(D$2:D$2001))/STDEV(D$2:D$2001) -> -0.64218677 | AC13: =(I13-AVERAGE(I$2:I$2001))/STDEV(I$2:I$2001) -> 0.68691707 | AD13: =(L13-AVERAGE(L$2:L$2001))/STDEV(L$2:L$2001) -> -0.77706312 | AE13: =(M13-AVERAGE(M$2:M$2001))/STDEV(M$2:M$2001) -> 0.81537049 | AF13: =(N13-AVERAGE(N$2:N$2001))/STDEV(N$2:N$2001) -> 2.4034392 | AG13: =(O13-AVERAGE(O$2:O$2001))/STDEV(O$2:O$2001) -> 1.7106641 | AH13: =IF(B13="Company","C3 - Corporate Buyers",IF(AND(H13="Investment",M13>'Segmentation Summary'!$C$1),"C1 - Global Investors",IF(AND(I13>=4,M13>'Segmentation Summary'!$C$1),"C4 - Luxury Investors",IF(AND(D13<'Segmentation Summary'!$C$2,J13=1),"C2 - First-Time Buyers","C5 - Other Individual Buyers")))) -> C3 - Corporate Buyers
... A2001: C0041 | B2001: Individual | C2001: Zain Horne | D2001: 57 | E2001: M | F2001: USA | G2001: Arizona | H2001: Home | I2001: 1 | J2001: 1 | K2001: Website | L2001: 5 | M2001: 1374460.8 | N2001: 274892.16 | O2001: 872.838 | P2001: 2 | Q2001: 3 | R2001: 2024-01-04 | S2001: 2025-01-10 | T2001: 1 | U2001: =IF(B2001="Individual",1,0) -> 1 | V2001: =IF(B2001="Company",1,0) -> 0 | W2001: =IF(H2001="Home",1,0) -> 1 | X2001: =IF(H2001="Investment",1,0) -> 0 | Y2001: =IF(K2001="Website",1,0) -> 1 | Z2001: =IF(K2001="Agency",1,0) -> 0 | AA2001: =IF(K2001="Client",1,0) -> 0 | AB2001: =(D2001-AVERAGE(D$2:D$2001))/STDEV(D$2:D$2001) -> 0.16508761 | AC2001: =(I2001-AVERAGE(I$2:I$2001))/STDEV(I$2:I$2001) -> -1.4353808 | AD2001: =(L2001-AVERAGE(L$2:L$2001))/STDEV(L$2:L$2001) -> 1.6047396 | AE2001: =(M2001-AVERAGE(M$2:M$2001))/STDEV(M$2:M$2001) -> 0.32799095 | AF2001: =(N2001-AVERAGE(N$2:N$2001))/STDEV(N$2:N$2001) -> -1.0355122 | AG2001: =(O2001-AVERAGE(O$2:O$2001))/STDEV(O$2:O$2001) -> -1.2488106 | AH2001: =IF(B2001="Company","C3 - Corporate Buyers",IF(AND(H2001="Investment",M2001>'Segmentation Summary'!$C$1),"C1 - Global Investors",IF(AND(I2001>=4,M2001>'Segmentation Summary'!$C$1),"C4 - Luxury Investors",IF(AND(D2001<'Segmentation Summary'!$C$2,J2001=1),"C2 - First-Time Buyers","C5 - Other Individual Buyers")))) -> C5 - Other Individual Buyers

Sheet How This Was Built
A1: How This Workbook Was Built
A3: 1. Data pipeline order
A4: SQL (clean + join clients & properties into client_features.csv) -> this Excel workbook
A5: (encoding + scaling) -> Tableau (clustering) -> Power BI (final live dashboard).
A7: 2. 'Client Features' sheet — Step 2: One-Hot Encoding
A8: Columns type_Individual, type_Company, purpose_Home, purpose_Investment, and the three
A9: referral_ columns are all formulas like =IF(ClientType="Individual",1,0) — this converts
A10: text categories into 0/1 numeric flags, which clustering algorithms need.
A12: 3. 'Client Features' sheet — Step 3: Feature Scaling
A13: The _z columns (age_z, satisfaction_z, etc.) are Z-scores:
A14: =(value - AVERAGE(column)) / STDEV(column)
A15: This puts every numeric feature on the same scale (mean 0, std dev 1) so that a feature
... A34: Geographic Map, Segment Insights), with filters for country/region/purpose/type.
